poked/__init__.py
poked/__main__.py
poked/cache.py
poked/client.py
poked/colors.py
poked/queries.py
poked/sprites.py
poked-0.10.1.dist-info/WHEEL
poked-0.10.1.dist-info/METADATA
poked-0.10.1.dist-info/RECORD
